copier_ProjectScaffolding_PythonPackageSample/EntryPoint.py
copier_ProjectScaffolding_PythonPackageSample/Math.py
copier_ProjectScaffolding_PythonPackageSample/__init__.py
copier_ProjectScaffolding_PythonPackageSample-0.1.0.dist-info/LICENSE.txt
copier_ProjectScaffolding_PythonPackageSample-0.1.0.dist-info/METADATA
copier_ProjectScaffolding_PythonPackageSample-0.1.0.dist-info/WHEEL
copier_ProjectScaffolding_PythonPackageSample-0.1.0.dist-info/entry_points.txt
copier_ProjectScaffolding_PythonPackageSample-0.1.0.dist-info/top_level.txt
copier_ProjectScaffolding_PythonPackageSample-0.1.0.dist-info/RECORD
